<?xml version="1.0" encoding="utf-8"?>
<timestamp>
  <time>
    <begin>25.7714</begin>
    <end>39.6272</end>
    <sentence>6</sentence>
    <sentence>7</sentence>
    <sentence>8</sentence>
  </time>
  <time>
    <begin>57.9185</begin>
    <end>72.2377</end>
    <sentence>12</sentence>
    <sentence>13</sentence>
    <sentence>14</sentence>
  </time>
  <time>
    <begin>127.195</begin>
    <end>140.792</end>
    <sentence>31</sentence>
    <sentence>32</sentence>
    <sentence>33</sentence>
  </time>
</timestamp>
